printdirtree/__init__.py
printdirtree/__main__.py
printdirtree-0.1.4.dist-info/LICENSE
printdirtree-0.1.4.dist-info/METADATA
printdirtree-0.1.4.dist-info/WHEEL
printdirtree-0.1.4.dist-info/entry_points.txt
printdirtree-0.1.4.dist-info/top_level.txt
printdirtree-0.1.4.dist-info/RECORD
