Metadata-Version: 2.1
Name: printdirtree
Version: 0.1.4
Summary: A CLI utility to print the directory tree structure with customizable exclusions.
Home-page: https://github.com/timf34/PrintDirTree
Author: Tim Farrelly
Author-email: timf34@gmail.com
Requires-Python: >=3.6
License-File: LICENSE
Requires-Dist: pyperclip
